cupy/__init__.py
cupy/_environment.py
cupy/_util.cpython-35m-x86_64-linux-gnu.so
cupy/_version.py
cupy/cudnn.cpython-35m-x86_64-linux-gnu.so
cupy/cusolver.py
cupy/cusparse.py
cupy/.data/_wheel.json
cupy/.data/include/cudnn.h
cupy/.data/lib/libcudnn.so.7
cupy/.data/lib/libnccl.so.2
cupy/_binary/__init__.py
cupy/_binary/elementwise.py
cupy/_binary/packing.py
cupy/_creation/__init__.py
cupy/_creation/basic.py
cupy/_creation/from_data.py
cupy/_creation/matrix.py
cupy/_creation/ranges.py
cupy/_functional/__init__.py
cupy/_functional/piecewise.py
cupy/_indexing/__init__.py
cupy/_indexing/generate.py
cupy/_indexing/indexing.py
cupy/_indexing/insert.py
cupy/_indexing/iterate.py
cupy/_io/__init__.py
cupy/_io/formatting.py
cupy/_io/npz.py
cupy/_io/text.py
cupy/_logic/__init__.py
cupy/_logic/comparison.py
cupy/_logic/content.py
cupy/_logic/ops.py
cupy/_logic/truth.py
cupy/_logic/type_test.py
cupy/_manipulation/__init__.py
cupy/_manipulation/add_remove.py
cupy/_manipulation/basic.py
cupy/_manipulation/dims.py
cupy/_manipulation/join.py
cupy/_manipulation/kind.py
cupy/_manipulation/rearrange.py
cupy/_manipulation/shape.py
cupy/_manipulation/split.py
cupy/_manipulation/tiling.py
cupy/_manipulation/transpose.py
cupy/_math/__init__.py
cupy/_math/arithmetic.py
cupy/_math/explog.py
cupy/_math/floating.py
cupy/_math/hyperbolic.py
cupy/_math/misc.py
cupy/_math/rational.py
cupy/_math/rounding.py
cupy/_math/special.py
cupy/_math/sumprod.py
cupy/_math/trigonometric.py
cupy/_math/ufunc.py
cupy/_math/window.py
cupy/_misc/__init__.py
cupy/_misc/memory_ranges.py
cupy/_misc/who.py
cupy/_padding/__init__.py
cupy/_padding/pad.py
cupy/_sorting/__init__.py
cupy/_sorting/count.py
cupy/_sorting/search.py
cupy/_sorting/sort.py
cupy/_statistics/__init__.py
cupy/_statistics/correlation.py
cupy/_statistics/histogram.py
cupy/_statistics/meanvar.py
cupy/_statistics/order.py
cupy/core/__init__.py
cupy/core/_accelerator.cpython-35m-x86_64-linux-gnu.so
cupy/core/_carray.cpython-35m-x86_64-linux-gnu.so
cupy_cuda90-8.6.0.dist-info/METADATA
cupy_cuda90-8.6.0.dist-info/WHEEL
cupy_cuda90-8.6.0.dist-info/license.rst
cupy_cuda90-8.6.0.dist-info/top_level.txt
cupy_cuda90-8.6.0.dist-info/RECORD
